robot_folders/__init__.py
robot_folders/main.py
robot_folders/commands/__init__.py
robot_folders/commands/active_environment.py
robot_folders/commands/adapt_environment.py
robot_folders/commands/add_environment.py
robot_folders/commands/cd.py
robot_folders/commands/change_environment.py
robot_folders/commands/clean.py
robot_folders/commands/delete_environment.py
robot_folders/commands/get_checkout_base_dir.py
robot_folders/commands/make.py
robot_folders/commands/manage_underlays.py
robot_folders/commands/run.py
robot_folders/commands/scrape_environment.py
robot_folders/helpers/ConfigParser.py
robot_folders/helpers/__init__.py
robot_folders/helpers/build_helpers.py
robot_folders/helpers/clean_helpers.py
robot_folders/helpers/compilation_db_helpers.py
robot_folders/helpers/config_helpers.py
robot_folders/helpers/directory_helpers.py
robot_folders/helpers/environment_helpers.py
robot_folders/helpers/exceptions.py
robot_folders/helpers/option_helpers.py
robot_folders/helpers/repository_helpers.py
robot_folders/helpers/ros_version_helpers.py
robot_folders/helpers/underlays.py
robot_folders/helpers/which.py
robot_folders/helpers/workspace_chooser.py
robot_folders/helpers/resources/__init__.py
robot_folders/helpers/resources/userconfig_distribute.yaml
robot_folders-0.7.0.data/scripts/rob_folders-complete.sh
robot_folders-0.7.0.data/scripts/rob_folders_get_source_command.py
robot_folders-0.7.0.data/scripts/rob_folders_source.sh
robot_folders-0.7.0.data/scripts/source_environment.sh
robot_folders-0.7.0.dist-info/METADATA
robot_folders-0.7.0.dist-info/WHEEL
robot_folders-0.7.0.dist-info/entry_points.txt
robot_folders-0.7.0.dist-info/top_level.txt
robot_folders-0.7.0.dist-info/RECORD
