Metadata-Version: 2.1
Name: robot_folders
Version: 0.7.0
Summary: robot_folders is your workspace handling utility around the ROS ecosystem.
Project-URL: Documentation, https://fzi-forschungszentrum-informatik.github.io/robot_folders/index.html
Project-URL: Changelog, https://github.com/fzi-forschungszentrum-informatik/robot_folders/releases
Project-URL: Repository, https://github.com/fzi-forschungszentrum-informatik/robot_folders.git
Requires-Python: >=3
Requires-Dist: Click >=8.0
Requires-Dist: gitpython
Requires-Dist: inquirer
Requires-Dist: PyYaml
Requires-Dist: vcstool
Provides-Extra: test
Requires-Dist: pytest ; extra == 'test'
Requires-Dist: pytest-mock ; extra == 'test'
Requires-Dist: pyfakefs ; extra == 'test'
